cli_mon_showdown/__init__.py
cli_mon_showdown/cli.py
cli_mon_showdown/gemini_agent.py
cli_mon_showdown/showdown_wrapper.py
cli_mon_showdown/pokemon-showdown/ARCHITECTURE.md
cli_mon_showdown/pokemon-showdown/CODEOWNERS
cli_mon_showdown/pokemon-showdown/COMMANDLINE.md
cli_mon_showdown/pokemon-showdown/CONTRIBUTING.md
cli_mon_showdown/pokemon-showdown/LICENSE
cli_mon_showdown/pokemon-showdown/PROTOCOL.md
cli_mon_showdown/pokemon-showdown/Procfile
cli_mon_showdown/pokemon-showdown/README.md
cli_mon_showdown/pokemon-showdown/build
cli_mon_showdown/pokemon-showdown/eslint-ps-standard.mjs
cli_mon_showdown/pokemon-showdown/eslint.config.mjs
cli_mon_showdown/pokemon-showdown/old-simulator-doc.txt
cli_mon_showdown/pokemon-showdown/package-lock.json
cli_mon_showdown/pokemon-showdown/package.json
cli_mon_showdown/pokemon-showdown/pokemon-showdown
cli_mon_showdown/pokemon-showdown/simulator-doc.txt
cli_mon_showdown/pokemon-showdown/tsconfig.json
cli_mon_showdown/pokemon-showdown/config/CUSTOM-RULES.md
cli_mon_showdown/pokemon-showdown/config/config-example.js
cli_mon_showdown/pokemon-showdown/config/config.js
cli_mon_showdown/pokemon-showdown/config/custom-example.css
cli_mon_showdown/pokemon-showdown/config/formats.ts
cli_mon_showdown/pokemon-showdown/config/hosts.csv
cli_mon_showdown/pokemon-showdown/config/proxies.csv
cli_mon_showdown/pokemon-showdown/config/avatars/README.md
cli_mon_showdown/pokemon-showdown/config/chat-plugins/README.md
cli_mon_showdown/pokemon-showdown/config/ladders/README.md
cli_mon_showdown/pokemon-showdown/data/FORMES.md
cli_mon_showdown/pokemon-showdown/data/abilities.ts
cli_mon_showdown/pokemon-showdown/data/aliases.ts
cli_mon_showdown/pokemon-showdown/data/conditions.ts
cli_mon_showdown/pokemon-showdown/data/formats-data.ts
cli_mon_showdown/pokemon-showdown/data/items.ts
cli_mon_showdown/pokemon-showdown/data/learnsets.ts
cli_mon_showdown/pokemon-showdown/data/moves.ts
cli_mon_showdown/pokemon-showdown/data/natures.ts
cli_mon_showdown-0.1.17.dist-info/LICENSE
cli_mon_showdown-0.1.17.dist-info/METADATA
cli_mon_showdown-0.1.17.dist-info/WHEEL
cli_mon_showdown-0.1.17.dist-info/entry_points.txt
cli_mon_showdown-0.1.17.dist-info/top_level.txt
cli_mon_showdown-0.1.17.dist-info/RECORD
