Metadata-Version: 2.1
Name: cli-mon-showdown
Version: 0.1.17
Summary: CLI-Mon Showdown: Terminal-based Pokemon battle CLI that drives official Pokemon Showdown
Author: papichoolo
Project-URL: Homepage, https://github.com/papichoolo/cli-mon-showdown
Project-URL: Repository, https://github.com/papichoolo/cli-mon-showdown
Project-URL: Issues, https://github.com/papichoolo/cli-mon-showdown/issues
Keywords: pokemon,showdown,cli,battle
Classifier: Development Status :: 3 - Alpha
Classifier: Intended Audience :: End Users/Desktop
Classifier: Programming Language :: Python
Classifier: Programming Language :: Python :: 3
Classifier: Programming Language :: Python :: 3.10
Classifier: Programming Language :: Python :: 3.11
Classifier: Programming Language :: Python :: 3.12
Classifier: Topic :: Games/Entertainment
Classifier: Topic :: Utilities
Requires-Python: >=3.10
License-File: LICENSE
Requires-Dist: google-genai>=0.3.0
Requires-Dist: pydantic>=2.5
